refkeys/__init__.py
refkeys-0.0.1.dist-info/METADATA
refkeys-0.0.1.dist-info/WHEEL
refkeys-0.0.1.dist-info/top_level.txt
refkeys-0.0.1.dist-info/RECORD
