Metadata-Version: 2.1
Name: refkeys
Version: 0.0.1
Summary: This repository contains a tool for secret-sharing among two parties.
Home-page: https://github.com/mr-ravin/refkeys
Author: Ravin Kumar
Author-email: mr.ravin_kumar@hotmail.com
License: UNKNOWN
Platform: UNKNOWN
Classifier: Programming Language :: Python :: 3
Classifier: License :: OSI Approved :: MIT License
Classifier: Operating System :: OS Independent
